anyone_protocol_sdk/__init__.py
anyone_protocol_sdk/binary.py
anyone_protocol_sdk/config.py
anyone_protocol_sdk/control.py
anyone_protocol_sdk/exceptions.py
anyone_protocol_sdk/models.py
anyone_protocol_sdk/process.py
anyone_protocol_sdk/socks.py
anyone_protocol_sdk-0.0.1b0.dist-info/METADATA
anyone_protocol_sdk-0.0.1b0.dist-info/WHEEL
anyone_protocol_sdk-0.0.1b0.dist-info/top_level.txt
anyone_protocol_sdk-0.0.1b0.dist-info/RECORD
